{
  "main": {
    "id": "ebc702efcf01541b",
    "type": "split",
    "children": [
      {
        "id": "ed39780fd09f5a77",
        "type": "tabs",
        "children": [
          {
            "id": "1aaf9a38b02ac28a",
            "type": "leaf",
            "state": {
              "type": "markdown",
              "state": {
                "file": "PLACES/LIBRARIES/Marshall Public Library.md",
                "mode": "source",
                "backlinks": false,
                "source": false
              },
              "icon": "lucide-file",
              "title": "Marshall Public Library"
            }
          }
        ]
      }
    ],
    "direction": "vertical"
  },
  "left": {
    "id": "d29572634973a0f8",
    "type": "split",
    "children": [
      {
        "id": "2bccd219956cfcf7",
        "type": "tabs",
        "children": [
          {
            "id": "dbfa8ac519a0bb94",
            "type": "leaf",
            "state": {
              "type": "file-explorer",
              "state": {
                "sortOrder": "alphabeticalReverse"
              },
              "icon": "lucide-folder-closed",
              "title": "Files"
            }
          },
          {
            "id": "5c9a03e2f4fc85c8",
            "type": "leaf",
            "state": {
              "type": "search",
              "state": {
                "query": "",
                "matchingCase": false,
                "explainSearch": false,
                "collapseAll": false,
                "extraContext": false,
                "sortOrder": "alphabetical"
              },
              "icon": "lucide-search",
              "title": "Search"
            }
          },
          {
            "id": "d5de9567351f0e96",
            "type": "leaf",
            "state": {
              "type": "bookmarks",
              "state": {},
              "icon": "lucide-bookmark",
              "title": "Bookmarks"
            }
          },
          {
            "id": "68a3da340333f42d",
            "type": "leaf",
            "state": {
              "type": "recent-files",
              "state": {},
              "icon": "clock",
              "title": "Recent Files"
            }
          },
          {
            "id": "51e0d7f20e7184ea",
            "type": "leaf",
            "state": {
              "type": "recent-files",
              "state": {},
              "icon": "clock",
              "title": "Recent Files"
            }
          }
        ]
      }
    ],
    "direction": "horizontal",
    "width": 272.50418853759766
  },
  "right": {
    "id": "6ce23fcd82f8b8f0",
    "type": "split",
    "children": [
      {
        "id": "47230a8d15685efb",
        "type": "tabs",
        "children": [
          {
            "id": "dd603d0cb422d730",
            "type": "leaf",
            "state": {
              "type": "backlink",
              "state": {
                "file": "PLACES/LIBRARIES/Marshall Public Library.md",
                "collapseAll": true,
                "extraContext": false,
                "sortOrder": "byModifiedTime",
                "showSearch": false,
                "searchQuery": "",
                "backlinkCollapsed": false,
                "unlinkedCollapsed": false
              },
              "icon": "links-coming-in",
              "title": "Backlinks for Marshall Public Library"
            }
          },
          {
            "id": "b82a52bf57d389e2",
            "type": "leaf",
            "state": {
              "type": "outgoing-link",
              "state": {
                "file": "PLACES/LIBRARIES/Marshall Public Library.md",
                "linksCollapsed": false,
                "unlinkedCollapsed": false
              },
              "icon": "links-going-out",
              "title": "Outgoing links from Marshall Public Library"
            }
          },
          {
            "id": "d91894ec936ba4ef",
            "type": "leaf",
            "state": {
              "type": "tag",
              "state": {
                "sortOrder": "alphabetical",
                "useHierarchy": true
              },
              "icon": "lucide-tags",
              "title": "Tags"
            }
          },
          {
            "id": "d7d4eece6e477aa5",
            "type": "leaf",
            "state": {
              "type": "outline",
              "state": {
                "file": "ORGANIZATIONS/PARTIES/GROUPS/Idaho Main Street Caucus.md"
              },
              "icon": "lucide-list",
              "title": "Outline of Idaho Main Street Caucus"
            }
          },
          {
            "id": "f1059e05e1c16478",
            "type": "leaf",
            "state": {
              "type": "all-properties",
              "state": {
                "sortOrder": "frequency",
                "showSearch": false,
                "searchQuery": ""
              },
              "icon": "lucide-archive",
              "title": "All properties"
            }
          },
          {
            "id": "b158b9c505382e9f",
            "type": "leaf",
            "state": {
              "type": "file-properties",
              "state": {
                "file": "ORGANIZATIONS/PARTIES/GROUPS/Idaho Main Street Caucus.md"
              },
              "icon": "lucide-info",
              "title": "File properties for Idaho Main Street Caucus"
            }
          },
          {
            "id": "090eff80fb4fcf9e",
            "type": "leaf",
            "state": {
              "type": "Strange New Worlds",
              "state": {},
              "icon": "lucide-file",
              "title": "Plugin no longer active"
            }
          },
          {
            "id": "703e18d46572efd5",
            "type": "leaf",
            "state": {
              "type": "Strange New Worlds",
              "state": {},
              "icon": "file-digit",
              "title": "Strange New Worlds"
            }
          }
        ],
        "currentTab": 1
      }
    ],
    "direction": "horizontal",
    "width": 519.5
  },
  "left-ribbon": {
    "hiddenItems": {
      "switcher:Open quick switcher": false,
      "graph:Open graph view": false,
      "command-palette:Open command palette": false,
      "canvas:Create new canvas": false,
      "daily-notes:Open today's daily note": false,
      "templates:Insert template": false
    }
  },
  "active": "dbfa8ac519a0bb94",
  "lastOpenFiles": [
    "PLACES/LIBRARIES",
    "TOPICS/drag.md",
    "TOPICS/drag queen story time.md",
    "PEOPLE/Richard Spencer.md",
    "SOURCES/x hey you make sure to link these/2017-02-12 - Buzzfeed News - Love Lives In Whitefish, Montana, But So Do Neo-Nazis.md",
    "TOPICS/gender identity.md",
    "ORGANIZATIONS/Reading Time with the Queens.md",
    "SOURCES/x hey you make sure to link these/Idaho State Journal 2023-02-17 Members of local Christian congregations hold sit-in protest against Pocatello drag queen reading program.md",
    "PLACES/LIBRARIES/Marshall Public Library.md",
    "PEOPLE/Larry Echo Hawk.md",
    "SOURCES/x hey you make sure to link these/2018-04-26 - Buzzfeed News - Could Paulette Jordan Be The First Native American Governor.md",
    "GOVERNMENTS/IDAHO - LEGISLATIVE/Idaho Legislature.md",
    "PLACES/LOCATIONS/Idaho Capitol.md",
    "GOVERNMENTS/USA - TRIBES/Coeur d'Alene Tribe.md",
    "ORGANIZATIONS/POLITICS/Health Freedom Idaho.md",
    "PEOPLE/Sara Walton Brady.md",
    "TOPICS/HEALTH/DISEASES/coronavirus.md",
    "SOURCES/x hey you make sure to link these/2020-04-22 - Buzzfeed - There's More To Know About The Video Of A Mother Arrested On A Playground For Violating Stay-At-Home Orders.md",
    "GOVERNMENTS/IDAHO - EXECUTIVE/COUNTIES & CITIES/city council.md",
    "SOURCES/x hey you make sure to link these/2016-08-12 - Sandpoint Reader - Anti-abortion protesters disrupt community.md",
    "SOURCES/x hey you make sure to link these/2023-08-13 - Sandpoint Reader - Woodward will seek Dist. 1 Senate seat.md",
    "SOURCES/x hey you make sure to link these/2023-08-01 - Idaho Capital Sun - Former Idaho congressional candidate named to GOP national committee.md",
    "SOURCES/x hey you make sure to link these/2023-12-14 - Idaho Statesman & ProPublica - Idaho Republicans are discussing a proposal that would make it easier to repair schools.md",
    "SOURCES/x hey you make sure to link these/2024-05-23 - Idaho Press - Governor seeks outside lawyer in ITD lawsuit.md",
    "SOURCES/x hey you make sure to link these/2024-01-04 - MOON - Turning to a Convention of States in Times of National Crisis is Not the Answer.md",
    "SOURCES/x hey you make sure to link these/2024-02-02 - Idaho Education News - The election money race; an early Top 10 list.md",
    "ATTACHMENTS/MAPS/Snake River Dams.jpg",
    "SOURCES/HEARINGS/2024",
    "X LABELER",
    "ATTACHMENTS/MAPS/Wildlife Management Units.png",
    "ATTACHMENTS/DOCUMENTS/Sign_Chart_Supplement.pdf",
    "ATTACHMENTS/DOCUMENTS/ID Property Tax Limitations and Initiatives 1978–present.pdf",
    "ATTACHMENTS/DOCUMENTS/Historic Survey of Roads in Idaho’s State Highway System Volume 1 - Historic Context.pdf",
    "ATTACHMENTS/DOCUMENTS/Broadband Strategic Plan.pdf",
    "ATTACHMENTS/DOCUMENTS",
    "ATTACHMENTS/TEMPLATES",
    "ATTACHMENTS/MAPS",
    "ATTACHMENTS/MAPS/Legislative District Map 2021.pdf",
    "Pasted image 20231121102332.png"
  ]
}